Metadata-Version: 2.1
Name: ibsplib
Version: 0.1.0
Summary: Python library for working with Quake 3 IBSP structures
Home-page: https://github.com/Mix-Anik/ibsplib
Author: Mix-Anik
License: MIT
Keywords: quake 3,q3,IBSP,BSP
Platform: UNKNOWN
License-File: LICENSE
